[
  {
    "adult": false,
    "backdrop_path": "/kBQpRO3ysVQBhe6hl0uzJDYLc1l.jpg",
    "genre_ids": [
      10749,
      28
    ],
    "id": 451396,
    "original_language": "hi",
    "original_title": "Yeh Dil Aashiqanaa",
    "overview": "Yeh Dil Ashiqana is the story of Karan and Pooja who are studying in the same college in Poona. They meet and fall in love and their romance progresses without any problems until one day while going to her brother's house in Mumbai.",
    "popularity": 2.423,
    "poster_path": "/9cw9yd7dJaVcf1Hd947Tyu1reaJ.jpg",
    "release_date": "18/01/2002",
    "title": "Yeh Dil Aashiqanaa",
    "video": false,
    "vote_average": 5.8,
    "vote_count": 4,
    "media_type": "movie"
  },
  {
    "adult": false,
    "backdrop_path": "/AspsIxsgWYlV2hL2WD2FHQo9eVe.jpg",
    "genre_ids": [
      80,
      53
    ],
    "id": 1112552,
    "original_language": "hi",
    "original_title": "कैनेडी",
    "overview": "An insomniac former cop, Kennedy has been presumed dead for years. Yet, in secret, he continues to serve a corrupt system while seeking redemption. Halfway between thriller and film noir, Kennedy chronicles a violent and bloody vendetta in the dark streets of Mumbai. At the rate of the murders, Kennedy's character reveals itself more and more and sinks into a spiral that seems to have no way out.",
    "popularity": 4.4746,
    "poster_path": "/AcJ9bkxzwJOZZs7d25aeKFU98ne.jpg",
    "release_date": "24/05/2023",
    "title": "Kennedy",
    "video": false,
    "vote_average": 7.4,
    "vote_count": 5,
    "media_type": "movie"
  },
  {
    "adult": false,
    "backdrop_path": "/lprsAHkwMxk2iC6VZxNmV0H7g1t.jpg",
    "genre_ids": [
      28,
      80,
      18
    ],
    "id": 781732,
    "original_language": "hi",
    "original_title": "Animal",
    "overview": "The hardened son of a powerful industrialist returns home after years abroad and vows to take bloody revenge on those threatening his father's life.",
    "popularity": 8.5387,
    "poster_path": "/hr9rjR3J0xBBKmlJ4n3gHId9ccx.jpg",
    "release_date": "01/12/2023",
    "title": "Animal",
    "video": false,
    "vote_average": 6.113,
    "vote_count": 172,
    "media_type": "movie"
  },
  {
    "adult": false,
    "backdrop_path": "/8XPPKEgO7sJs0rP53h3kUPT1tTW.jpg",
    "genre_ids": [
      27,
      14,
      18
    ],
    "id": 718833,
    "original_language": "hi",
    "original_title": "Bokshi",
    "overview": "Anahita, traumatised by the brutal disappearance of her mother, finds comfort in Shalini, her history teacher. On an unconventional school excursion to a mysterious prehistoric site, she confronts her terrifying destiny.",
    "popularity": 5.2609,
    "poster_path": "/9Loc2q3gO1HWolw0o6kLaMXrocS.jpg",
    "release_date": "31/01/2025",
    "title": "Bokshi",
    "video": false,
    "vote_average": 6,
    "vote_count": 1,
    "media_type": "movie"
  },
  {
    "adult": false,
    "backdrop_path": "/A5ajQPdmA4P87vTpOXmFetA14fx.jpg",
    "genre_ids": [
      80,
      28,
      53
    ],
    "id": 1306845,
    "original_language": "hi",
    "original_title": "जाट",
    "overview": "A mysterious stranger journeys to a remote town controlled by a callous crime lord, with one violent mission — restoring justice to its people.",
    "popularity": 2.7248,
    "poster_path": "/guTflsCTgLNqTbpHTi9gJANk1Rf.jpg",
    "release_date": "10/04/2025",
    "title": "Jaat",
    "video": false,
    "vote_average": 6.2,
    "vote_count": 30,
    "media_type": "movie"
  },
  {
    "adult": false,
    "backdrop_path": "/v9w0xds8GUzOwHTZRuw2yeObRzD.jpg",
    "genre_ids": [
      18
    ],
    "id": 1227739,
    "original_language": "hi",
    "original_title": "होमबाउंड",
    "overview": "Two childhood friends from a small North Indian village chase a police job that promises them the dignity they’ve long been denied. But as they inch closer to their dream, mounting desperation threatens the bond that holds them together.",
    "popularity": 7.6709,
    "poster_path": "/vyezjSvSdLO0bvr6jSNuFi6yuiw.jpg",
    "release_date": "26/09/2025",
    "title": "Homebound",
    "video": false,
    "vote_average": 7.719,
    "vote_count": 32,
    "media_type": "movie"
  },
  {
    "adult": false,
    "backdrop_path": "/iQGmmI5VwNW2cjrF2uQF8VhBGcw.jpg",
    "genre_ids": [
      10749,
      35
    ],
    "id": 1407523,
    "original_language": "hi",
    "original_title": "तू मेरी मैं तेरा मैं तेरा तू मेरी",
    "overview": "When a carefree NRI wedding planner and a headstrong novelist collide during a wild summer in Croatia, sparks fly in ways neither expected. What begins as playful clashes soon transforms into something deeper – only to be tested when love, family, and tradition pull them in opposite directions.",
    "popularity": 1.6994,
    "poster_path": "/4mJ4xhjBTBF8GOtsfr78Ebp76vS.jpg",
    "release_date": "24/12/2025",
    "title": "Tu Meri Main Tera Main Tera Tu Meri",
    "video": false,
    "vote_average": 3,
    "vote_count": 2,
    "media_type": "movie"
  },
  {
    "adult": false,
    "backdrop_path": "/fzo85eKFEjfmJ781gubJQjpQAwF.jpg",
    "genre_ids": [
      28,
      18,
      10752
    ],
    "id": 1213898,
    "original_language": "hi",
    "original_title": "बॉर्डर २",
    "overview": "During the events of the 1971 Indo-Pak war, a new generation of young Indian warriors were getting ready to defend the nation from an even bigger threat to the Indian motherland.",
    "popularity": 21.0052,
    "poster_path": "/AmrCgmDPEJ6QxllS1rhjYwgO9Wb.jpg",
    "release_date": "23/01/2026",
    "title": "Border 2",
    "video": false,
    "vote_average": 7.6,
    "vote_count": 7,
    "media_type": "movie"
  },
  {
    "adult": false,
    "backdrop_path": "/5z7eorMubo7nB11P8s5a0GMXf2D.jpg",
    "genre_ids": [
      80,
      18,
      53
    ],
    "id": 1595507,
    "original_language": "hi",
    "original_title": "वध 2",
    "overview": "A police officer's pursuit of truth in a shocking prison crime intertwines with the lives of a widowed prison guard and a soon to be released inmate, unravelling a web of morality and redemption.",
    "popularity": 0.383,
    "poster_path": "/pOJAaLMsc7T5rwVDTA7SRg9SAEU.jpg",
    "release_date": "06/02/2026",
    "title": "Vadh 2",
    "video": false,
    "vote_average": 0,
    "vote_count": 0,
    "media_type": "movie"
  },
  {
    "adult": false,
    "backdrop_path": null,
    "genre_ids": [
      10751,
      35
    ],
    "id": 1587124,
    "original_language": "hi",
    "original_title": "Bhabiji Ghar Par Hain!",
    "overview": "In a whirlwind of misunderstandings, two rival neighbours, Vibhuti and Tiwari, find themselves on a riotous road trip with their wives, only to get tangled up with lovable gangster brothers, Shanti and Kranti, who turn a simple journey into an unforgettable comedy of errors.",
    "popularity": 0.9273,
    "poster_path": "/v8G1NudtXq7BP56TgmAfpDx10FQ.jpg",
    "release_date": "06/02/2026",
    "title": "Bhabiji Ghar Par Hain!",
    "video": false,
    "vote_average": 0,
    "vote_count": 0,
    "media_type": "movie"
  },
  {
    "adult": false,
    "backdrop_path": null,
    "genre_ids": [
      10749,
      35
    ],
    "id": 1523598,
    "original_language": "hi",
    "original_title": "Oh Laila Tere Peeche Padd Gaye Apni Jaan Nisaar Kar Gaye",
    "overview": "3 Majnus And 33 Lailas !!!!!!  Just Imagine The Chaos................",
    "popularity": 0.0214,
    "poster_path": "/cDYJsnHQsgi6fMRkp9SGlHxzPXz.jpg",
    "release_date": "07/02/2026",
    "title": "Oh Laila Tere Peeche Padd Gaye Apni Jaan Nisaar Kar Gaye",
    "video": false,
    "vote_average": 0,
    "vote_count": 0,
    "media_type": "movie"
  },
  {
    "adult": false,
    "backdrop_path": "/aSeY6T4sgFX75Zi6IErIj2QUj7Y.jpg",
    "genre_ids": [
      53,
      10749,
      12
    ],
    "id": 1446616,
    "original_language": "hi",
    "original_title": "तू या मैं",
    "overview": "Two content creators get stuck in an empty pool and must fight for their survival against a ferocious, blood-thirsty creature.",
    "popularity": 1.2232,
    "poster_path": "/nUPnA0I1MTaZRVCsUQc5DS5JA8W.jpg",
    "release_date": "13/02/2026",
    "title": "Tu Yaa Main",
    "video": false,
    "vote_average": 0,
    "vote_count": 0,
    "media_type": "movie"
  },
  {
    "adult": false,
    "backdrop_path": "/6KZxyglIGJrW5RplMXhXwB2YDLN.jpg",
    "genre_ids": [
      80,
      18,
      28
    ],
    "id": 1275574,
    "original_language": "hi",
    "original_title": "ओ रोमियो",
    "overview": "What fate awaits a stone-hearted gangster, a bloodthirsty womaniser, when true love claims him, helpless and unguarded- a gang war that shakes the entire underworld and crime syndicate to their very roots.",
    "popularity": 1.48,
    "poster_path": "/Apqc5JSXQtUJPcBGm6tBO6wQaoq.jpg",
    "release_date": "13/02/2026",
    "title": "O'Romeo",
    "video": false,
    "vote_average": 0,
    "vote_count": 0,
    "media_type": "movie"
  },
  {
    "adult": false,
    "backdrop_path": null,
    "genre_ids": [
      10749
    ],
    "id": 1525100,
    "original_language": "hi",
    "original_title": "Haye Hukku Haye Hukku Haaye Haaye Haaye",
    "overview": "Daksh and Insha Are Close Friends Who Have Never Seen Each Other Romantically, But Their Families Misinterpret Their Bond And Arrange Their Engagement  Desperate To Escape , They Make A Dramatic Announcement - Daksh Declares That He Is Gay, While Insha A Lesbian - And The Engagement Is Immediately Called Off Leaving Their Families In Shock , What Begins As A Silly Plan To Avoid Marriage Slowly Backfires When Daksh And Insha, Spending More Time Together Amidst The Chaos , Begin To Develop Real Feelings\r Now Trapped By Their Own Lie , They Must Find The Courage To Confess Both The Truth And Their Love Turning The Raita They Created Into A Happily-Ever-After",
    "popularity": 0.0741,
    "poster_path": "/gRYPJYSNYxMJf2GAUIYK0MtT5mm.jpg",
    "release_date": "14/02/2026",
    "title": "Haye Hukku Haye Hukku Haaye Haaye Haaye",
    "video": false,
    "vote_average": 0,
    "vote_count": 0,
    "media_type": "movie"
  },
  {
    "adult": false,
    "backdrop_path": "/1lhJYCkWU5HnnRFEza8GuJOdfPz.jpg",
    "genre_ids": [
      80,
      18,
      53
    ],
    "id": 1435606,
    "original_language": "hi",
    "original_title": "अस्सी",
    "overview": "An investigative courtroom drama based on the alarming statistic of nearly eighty sexual assault cases reported daily in India. In just one day. Every day.",
    "popularity": 0.9201,
    "poster_path": "/wBs2SZKKaYZJDmq01maIjdZwUT0.jpg",
    "release_date": "20/02/2026",
    "title": "Assi",
    "video": false,
    "vote_average": 0,
    "vote_count": 0,
    "media_type": "movie"
  },
  {
    "adult": false,
    "backdrop_path": "/ApvEXB4XrrsgUHFlKDG1Z1V3MWC.jpg",
    "genre_ids": [
      10749,
      18
    ],
    "id": 1241693,
    "original_language": "hi",
    "original_title": "दो दीवाने शहर में",
    "overview": "Two socially awkward millennials in Mumbai find love while struggling with self-acceptance. As they battle insecurities and societal pressure, their journey takes them from city chaos to mountain serenity.",
    "popularity": 0.7574,
    "poster_path": "/p8yPjT9NAH87oD9TedclRaAW7RY.jpg",
    "release_date": "20/02/2026",
    "title": "Do Deewane Seher Mein",
    "video": false,
    "vote_average": 0,
    "vote_count": 0,
    "media_type": "movie"
  },
  {
    "adult": false,
    "backdrop_path": null,
    "genre_ids": [
      12,
      35
    ],
    "id": 1524093,
    "original_language": "hi",
    "original_title": "Jim Jam Jelly",
    "overview": "Get Ready For The Ultimate Adventure \"Jee Le Zaraa\" Join The Journey Of Friendship , Self-Discovery And Thrilling Experiences With Laughter , Excitement And Unforgettable Moments , This Series Will Take You On A Ride Of A Lifetime",
    "popularity": 0.0071,
    "poster_path": "/jSGFX5RHaFk0M7H8Ug7OscUcuO7.jpg",
    "release_date": "03/03/2026",
    "title": "Jim Jam Jelly",
    "video": false,
    "vote_average": 0,
    "vote_count": 0,
    "media_type": "movie"
  },
  {
    "adult": false,
    "backdrop_path": null,
    "genre_ids": [
      35
    ],
    "id": 1320660,
    "original_language": "hi",
    "original_title": "Pati Patni aur Woh Do",
    "overview": "A Sequel to Pati Patni Aur Woh",
    "popularity": 2.4181,
    "poster_path": "/6chLYoOPhhYjyQh7LnDOsotxbvP.jpg",
    "release_date": "04/03/2026",
    "title": "Pati Patni aur Woh Do",
    "video": false,
    "vote_average": 0,
    "vote_count": 0,
    "media_type": "movie"
  },
  {
    "adult": false,
    "backdrop_path": null,
    "genre_ids": [
      10749,
      18,
      10402
    ],
    "id": 1624339,
    "original_language": "hi",
    "original_title": "Jab We Met-Re Release",
    "overview": "A depressed wealthy businessman finds his life changing after he meets a spunky and care-free young woman.",
    "popularity": 0.2135,
    "poster_path": "/sUws8VRN2w8GuBPbIrAuQWvdbCG.jpg",
    "release_date": "13/03/2026",
    "title": "Jab We Met-Re Release",
    "video": false,
    "vote_average": 0,
    "vote_count": 0,
    "media_type": "movie"
  },
  {
    "adult": false,
    "backdrop_path": null,
    "genre_ids": [
      18
    ],
    "id": 1215191,
    "original_language": "hi",
    "original_title": "Gabru",
    "overview": "A social drama that is a very heart-warming tale which celebrates the undying human spirit. The core plot of the film chronicles the journey of Sunny Deol and a child artist, undergoing troubles in their respective lives.",
    "popularity": 3.1684,
    "poster_path": "/fu16F44fck96HHb4ed9RcEPszJp.jpg",
    "release_date": "13/03/2026",
    "title": "Gabru",
    "video": false,
    "vote_average": 0,
    "vote_count": 0,
    "media_type": "movie"
  },
  {
    "adult": false,
    "backdrop_path": "/owQeDouUZ6wI6f1aTOYEFd511zn.jpg",
    "genre_ids": [
      28,
      53
    ],
    "id": 1582770,
    "original_language": "hi",
    "original_title": "धुरंधर: द रिवेंज",
    "overview": "As rival gangs, corrupt officials and a ruthless Major Iqbal close in, Hamza's mission for his country spirals into a bloody personal war where the line between patriot and monster disappears in the streets of Lyari.",
    "popularity": 9.8297,
    "poster_path": "/yfikYFZwy3IAq3qvCW77SNZoYI7.jpg",
    "release_date": "19/03/2026",
    "title": "Dhurandhar: The Revenge",
    "video": false,
    "vote_average": 0,
    "vote_count": 0,
    "media_type": "movie"
  },
  {
    "adult": false,
    "backdrop_path": null,
    "genre_ids": [
      27
    ],
    "id": 728405,
    "original_language": "hi",
    "original_title": "Rosie: The Saffron Chapter",
    "overview": "Upcoming Hindi movie",
    "popularity": 3.1121,
    "poster_path": "/7Vjv3nE8Z7fk0kHSRt4PvY4rvrk.jpg",
    "release_date": "26/03/2026",
    "title": "Rosie: The Saffron Chapter",
    "video": false,
    "vote_average": 0,
    "vote_count": 0,
    "media_type": "movie"
  },
  {
    "adult": false,
    "backdrop_path": null,
    "genre_ids": [
      28
    ],
    "id": 1621564,
    "original_language": "hi",
    "original_title": "Hum Mein Shahenshah Koun",
    "overview": "No description",
    "popularity": 0.133,
    "poster_path": "/uom1jg743fr7psigIF6T5j5hDfV.jpg",
    "release_date": "01/04/2026",
    "title": "Hum Mein Shahenshah Koun",
    "video": false,
    "vote_average": 0,
    "vote_count": 0,
    "media_type": "movie"
  },
  {
    "adult": false,
    "backdrop_path": "/36GbUxGLMzQstNmWbRetQaPjR1K.jpg",
    "genre_ids": [
      16,
      28,
      12,
      14
    ],
    "id": 1532239,
    "original_language": "hi",
    "original_title": "Chiranjeevi Hanuman: The Eternal",
    "overview": "An AI-generated film about the Hindu god Hanuman; it will draw from the sacred texts of Indian epic 'Ramayana' and Puranic literature to create what producers describe as an “awe-inspiring, visual odyssey designed to be enjoyed as a shared experience in theaters.”",
    "popularity": 0.2773,
    "poster_path": "/5PJNeckEmOcMVh8xT4YVjdUf5nj.jpg",
    "release_date": "01/04/2026",
    "title": "Chiranjeevi Hanuman: The Eternal",
    "video": false,
    "vote_average": 0,
    "vote_count": 0,
    "media_type": "movie"
  },
  {
    "adult": false,
    "backdrop_path": "/rILHQgcOgE3DPsYSFWAuKJ7P0wk.jpg",
    "genre_ids": [
      28,
      18
    ],
    "id": 1475768,
    "original_language": "hi",
    "original_title": "Battle Of Galwan",
    "overview": "Based on the events that took place between the Indian and Chinese troops at the Galwan region on June 15, 2020 when 200 Indian soldiers bravely defended their territory against a force of 1200 Chinese Liberation Army soldiers",
    "popularity": 0.535,
    "poster_path": "/69pe5Y3ubSsrpNKoySqA3luIMmg.jpg",
    "release_date": "17/04/2026",
    "title": "Battle Of Galwan",
    "video": false,
    "vote_average": 0,
    "vote_count": 0,
    "media_type": "movie"
  },
  {
    "adult": false,
    "backdrop_path": "/x2SfNDCuPwdZBstt79XHgMat38M.jpg",
    "genre_ids": [
      18,
      10749,
      10402
    ],
    "id": 453989,
    "original_language": "hi",
    "original_title": "Tu Meri Zindagi Hai",
    "overview": "A self-destructive, tormented rockstar finds his life and love transformed through an intense romantic journey shaped by music and emotion.",
    "popularity": 0.6227,
    "poster_path": "/dF1P8wT9cDcgNMfgngiYj4oR7qG.jpg",
    "release_date": "01/05/2026",
    "title": "Tu Meri Zindagi Hai",
    "video": false,
    "vote_average": 0,
    "vote_count": 0,
    "media_type": "movie"
  },
  {
    "adult": false,
    "backdrop_path": null,
    "genre_ids": [
      10749,
      18
    ],
    "id": 1235057,
    "original_language": "hi",
    "original_title": "Love & War",
    "overview": "A love story set against the backdrop of a war.",
    "popularity": 6.5404,
    "poster_path": "/iy4O9s3GyUoZqudsfFLuVSXLbgT.jpg",
    "release_date": "14/08/2026",
    "title": "Love and War",
    "video": false,
    "vote_average": 0,
    "vote_count": 0,
    "media_type": "movie"
  },
  {
    "adult": false,
    "backdrop_path": "/9jIJrwbDTH92027rIrR2R0HM0Qe.jpg",
    "genre_ids": [
      53,
      18,
      9648
    ],
    "id": 1269325,
    "original_language": "hi",
    "original_title": "Drishyam 3",
    "overview": "Third and final chapter of the Drishyam series.",
    "popularity": 0.3093,
    "poster_path": "/43HEnZBiZ0MZUbtBxMwnrvJNlt.jpg",
    "release_date": "02/10/2026",
    "title": "Drishyam 3",
    "video": false,
    "vote_average": 0,
    "vote_count": 0,
    "media_type": "movie"
  },
  {
    "adult": false,
    "backdrop_path": "/prbMZ3DPf8taS6JYQd6igPnm2mA.jpg",
    "genre_ids": [
      28,
      18,
      14
    ],
    "id": 656908,
    "original_language": "hi",
    "original_title": "रामायण",
    "overview": "First part of the epic Ramayana duology.",
    "popularity": 5.3873,
    "poster_path": "/f3yZZw7zIsWo6m9xJStfjDauIZX.jpg",
    "release_date": "06/11/2026",
    "title": "Ramayana",
    "video": false,
    "vote_average": 0,
    "vote_count": 0,
    "media_type": "movie"
  },
  {
    "adult": false,
    "backdrop_path": "/tInyP783MTHruydmJMSo7mfag1U.jpg",
    "genre_ids": [
      28,
      53
    ],
    "id": 1145110,
    "original_language": "hi",
    "original_title": "King",
    "overview": "Mentor and disciple embark on a perilous journey, pushing their survival skills to the limit against overwhelming odds and unforgiving environments.",
    "popularity": 4.5214,
    "poster_path": "/74fHULlTBMGGLusfFBVAkMAZbce.jpg",
    "release_date": "24/12/2026",
    "title": "King",
    "video": false,
    "vote_average": 0,
    "vote_count": 0,
    "media_type": "movie"
  },
  {
    "adult": false,
    "backdrop_path": "/hB1t79Cm2tcKdy1YSNrxvZCd8vS.jpg",
    "genre_ids": [
      18
    ],
    "id": 1604487,
    "original_language": "hi",
    "original_title": "The Audition",
    "overview": "A struggling actor, Nikhil Dagga , 31 stands at the brink of surrender. Broke and beaten down, he retreats to a claustrophobic Mumbai apartment where intrusive neighbors and mounting debts test his resolve. When his final chance at redemption collapses, one desperate, late-night performance becomes an unexpected act of rebellion.",
    "popularity": 0.042,
    "poster_path": "/2gfU7rNQopquBFyuAU4Cdt0gbuj.jpg",
    "release_date": "27/12/2026",
    "title": "The Audition",
    "video": false,
    "vote_average": 0,
    "vote_count": 0,
    "media_type": "movie"
  },
  {
    "adult": false,
    "backdrop_path": null,
    "genre_ids": [
      27,
      53
    ],
    "id": 1528042,
    "original_language": "hi",
    "original_title": "Mouthwashing : The Film",
    "overview": "The Indian Film Adaptation Of The Bone-Chilling Video Game - Mouthwashing",
    "popularity": 0.1728,
    "poster_path": "/maufjIWidCpVxKKyqZ9qT0z9Gvo.jpg",
    "release_date": "05/01/2027",
    "title": "Mouthwashing : The Film",
    "video": false,
    "vote_average": 0,
    "vote_count": 0,
    "media_type": "movie"
  },
  {
    "adult": false,
    "backdrop_path": "/rPiCPzCZ6lBhnlFoJkvtCd47imp.jpg",
    "genre_ids": [
      18,
      28
    ],
    "id": 1511426,
    "original_language": "hi",
    "original_title": "BAHUBURA",
    "overview": "Mr. Teacher, a quiet and principled schoolteacher, is devastated after losing his only child in a tragic road accident. The very same day, at the accident site, he comes across another injured boy-abandoned, nameless, and unconscious. Everyone around looks the other way, but Mr. Teacher steps in to help. As he nurses the boy back to health, he discovers the child is a victim of a deeper evil-caught in the clutches of a trafficking network. What begins as an act of kindness becomes a mission of justice.",
    "popularity": 0.0357,
    "poster_path": "/yQE1bWmNYxLtDfx5jPzR0CghTlv.jpg",
    "release_date": "10/03/2027",
    "title": "BAHUBURA",
    "video": false,
    "vote_average": 0,
    "vote_count": 0,
    "media_type": "movie"
  },
  {
    "adult": false,
    "backdrop_path": null,
    "genre_ids": [
      27,
      35
    ],
    "id": 1374067,
    "original_language": "hi",
    "original_title": "स्त्री 3",
    "overview": "The eighth installment in the Maddock Supernatural Cinematic Universe. Plot TBA.",
    "popularity": 2.0078,
    "poster_path": "/uRCb1gfrwhzBf6DAxa9l4dL0vd9.jpg",
    "release_date": "13/08/2027",
    "title": "Stree 3",
    "video": false,
    "vote_average": 0,
    "vote_count": 0,
    "media_type": "movie"
  },
  {
    "adult": false,
    "backdrop_path": null,
    "genre_ids": [
      27,
      35,
      28
    ],
    "id": 1112424,
    "original_language": "hi",
    "original_title": "भेड़िया 2",
    "overview": "The thirteenth installment in the Maddock Supernatural Cinematic Universe. Plot TBA.",
    "popularity": 1.4054,
    "poster_path": "/gMmZqma6Arrxbmc33Ab8HSgZTIP.jpg",
    "release_date": "13/08/2027",
    "title": "Bhediya 2:  The Beginning of End",
    "video": false,
    "vote_average": 0,
    "vote_count": 0,
    "media_type": "movie"
  },
  {
    "adult": false,
    "backdrop_path": null,
    "genre_ids": [
      27,
      35
    ],
    "id": 1411090,
    "original_language": "hi",
    "original_title": "चामुंडा",
    "overview": "The seventh installment in the Maddock Supernatural Cinematic Universe. Plot TBA.",
    "popularity": 0.915,
    "poster_path": "/eUJbBoFYUPCYsmxCNKad4O4xhjI.jpg",
    "release_date": "03/12/2027",
    "title": "Chamunda",
    "video": false,
    "vote_average": 0,
    "vote_count": 0,
    "media_type": "movie"
  },
  {
    "adult": false,
    "backdrop_path": null,
    "genre_ids": [
      28
    ],
    "id": 1387155,
    "original_language": "hi",
    "original_title": "Mahavatar",
    "overview": "Mahavatar tells the epic story of Parashurama, the immortal warrior of dharma from Hindu mythology, whose journey spans ages as he upholds righteousness against the forces of darkness.",
    "popularity": 0.1595,
    "poster_path": "/rOvcqUpQEnbCYLOxFZC5DNoNzgy.jpg",
    "release_date": "24/12/2027",
    "title": "Mahavatar",
    "video": false,
    "vote_average": 0,
    "vote_count": 0,
    "media_type": "movie"
  },
  {
    "adult": false,
    "backdrop_path": null,
    "genre_ids": [
      27,
      35
    ],
    "id": 1382950,
    "original_language": "hi",
    "original_title": "महा मुंज्या",
    "overview": "The ninth installment in the Maddock Supernatural Cinematic Universe. Plot TBA.",
    "popularity": 0.612,
    "poster_path": "/oT8gql42lcUb0WMLTvuh0SJiC18.jpg",
    "release_date": "24/12/2027",
    "title": "Maha Munjya",
    "video": false,
    "vote_average": 0,
    "vote_count": 0,
    "media_type": "movie"
  },
  {
    "adult": false,
    "backdrop_path": null,
    "genre_ids": [
      27,
      35,
      28
    ],
    "id": 1411093,
    "original_language": "hi",
    "original_title": "पहला महायुद्ध",
    "overview": "The tenth installment in the Maddock Supernatural Cinematic Universe. Plot TBA.",
    "popularity": 0.4521,
    "poster_path": "/bmxKmw2u7W6zm2eVfuc8wtk6BKb.jpg",
    "release_date": "11/08/2028",
    "title": "Pehla Mahayudh",
    "video": false,
    "vote_average": 0,
    "vote_count": 0,
    "media_type": "movie"
  },
  {
    "adult": false,
    "backdrop_path": null,
    "genre_ids": [
      28,
      35,
      27
    ],
    "id": 1411095,
    "original_language": "hi",
    "original_title": "दूसरा महायुद्ध",
    "overview": "The eleventh installment in the Maddock Supernatural Cinematic Universe. Plot TBA.",
    "popularity": 0.3653,
    "poster_path": "/3eTCJq3M5KKnnAW3Cwvy1h9Ln4I.jpg",
    "release_date": "18/10/2028",
    "title": "Doosara Mahayudh",
    "video": false,
    "vote_average": 0,
    "vote_count": 0,
    "media_type": "movie"
  }
]